12주차/BCDCounter.v
module BCDCounter(reset, stepclk, updown, cnt_out);
	input reset, stepclk, updown;
	output [3:0] cnt_out;

	wire [3:0] cnt_out;

	parameter S0 = 0, S1 = 1, S2 = 2, S3 = 3, S4 = 4, S5 = 5, S6 = 6, S7 = 7, S8 = 8, S9 = 9;
	reg [3:0] state = S0;

	always @ (posedge stepclk or negedge reset)
		begin
			if (~reset)
				state = S0;
			else
				case(state)
					S0:
						if(~updown)	state = S1;
						else		state = S9;
					S1:
						if(~updown)	state = S2;
						else		state = S0;
					S2:
						if(~updown)	state = S3;
						else		state = S1;
					S3:
						if(~updown)	state = S4;
						else		state = S2;
					S4:
						if(~updown)	state = S5;
						else		state = S3;
					S5:
						if(~updown)	state = S6;
						else		state = S4;
					S6:
						if(~updown)	state = S7;
						else		state = S5;
					S7:
						if(~updown)	state = S8;
						else		state = S6;
					S8:
						if(~updown)	state = S9;
						else		state = S7;
					S9:
						if(~updown)	state = S0;
						else		state = S8;
				endcase
		end

	assign cnt_out = state;
endmodule

12주차/tb_BCDCounter.v
`timescale 1ns/10ps

module tb_BCDCounter;
	reg reset, stepclk, updown;
	wire [3:0] cnt_out;

	BCDCounter tb(reset, stepclk, updown, cnt_out);

	initial
		begin
			$dumpfile("test_BCDCounter_out.vcd");
			$dumpvars(-1, tb);
			$monitor("%b", cnt_out);
		end

	initial
		stepclk = 0;

	always
		#50 stepclk = !stepclk;

	initial
		begin
			reset = 1; updown = 0; #50;
			reset = 0; updown = 0; #70;
			reset = 1; updown = 1; #1000;
			reset = 1; updown = 0; #1000;
			$finish;
		end
endmodule

12주차/test_BCDCounter_out.vcd
$date
	Mon Nov 23 00:27:53 2020
$end
$version
	Icarus Verilog
$end
$timescale
	10ps
$end
$scope module tb_BCDCounter $end
$scope module tb $end
$var wire 4 ! cnt_out [3:0] $end
$var wire 1 " reset $end
$var wire 1 # stepclk $end
$var wire 1 $ updown $end
$var reg 4 % state [3:0] $end
$upscope $end
$upscope $end
$enddefinitions $end
#0
$dumpvars
b0 %
0$
0#
1"
b0 !
$end
#5000
0"
1#
#10000
0#
#12000
1$
1"
#15000
b1001 !
b1001 %
1#
#20000
0#
#25000
b1000 !
b1000 %
1#
#30000
0#
#35000
b111 !
b111 %
1#
#40000
0#
#45000
b110 !
b110 %
1#
#50000
0#
#55000
b101 !
b101 %
1#
#60000
0#
#65000
b100 !
b100 %
1#
#70000
0#
#75000
b11 !
b11 %
1#
#80000
0#
#85000
b10 !
b10 %
1#
#90000
0#
#95000
b1 !
b1 %
1#
#100000
0#
#105000
b0 !
b0 %
1#
#110000
0#
#112000
0$
#115000
b1 !
b1 %
1#
#120000
0#
#125000
b10 !
b10 %
1#
#130000
0#
#135000
b11 !
b11 %
1#
#140000
0#
#145000
b100 !
b100 %
1#
#150000
0#
#155000
b101 !
b101 %
1#
#160000
0#
#165000
b110 !
b110 %
1#
#170000
0#
#175000
b111 !
b111 %
1#
#180000
0#
#185000
b1000 !
b1000 %
1#
#190000
0#
#195000
b1001 !
b1001 %
1#
#200000
0#
#205000
b0 !
b0 %
1#
