9주차/XOR_Adder.v
module XOR_Adder(a, b, c, cin, s);
	input [3:0] a, b;
	input [2:0] c;
	input cin;
	output [3:0] s;

	wire [3:0] s;

	assign s[0] = a[0]^b[0]^cin;
	assign s[1] = a[1]^b[1]^c[0];
	assign s[2] = a[2]^b[2]^c[1];
	assign s[3] = a[3]^b[3]^c[2];

endmodule

9주차/CLL.v
module CLL(p, g, cin, cout);
	input [3:0] p, g;
	input cin;
	output [3:0] cout;

	reg [3:0] cout;

	always@(p or g)
		begin
			cout[0] = g[0]|(cin&p[0]);
			cout[1] = g[1]|(g[0]&p[1])|(cin&p[0]&p[1]);
			cout[2] = g[2]|(g[1]&p[2])|(g[0]&p[1]&p[2])|(cin&p[0]&p[1]&p[2]);
			cout[3] = g[3]|(g[2]&p[3])|(g[1]&p[2]&p[3])|(g[0]&p[1]&p[2]&p[3])|(cin&p[0]&p[1]&p[2]&p[3]);
		end
endmodule

9주차/PG.v
module PG(a, b, p, g);
	input a, b;
	output p, g;

	assign p = a^b;
	assign g = a&b;
endmodule

9주차/PG_four.v
module PG_four(a, b, p, g);
	input [3:0] a, b;
	output [3:0]  p, g;

	wire [3:0] p, g;

	PG pg0(a[0], b[0], p[0], g[0]);
	PG pg1(a[1], b[1], p[1], g[1]);
	PG pg2(a[2], b[2], p[2], g[2]);
	PG pg3(a[3], b[3], p[3], g[3]);

endmodule

9주차/CLA.v
module CLA_four(a, b, cin, s, cout);
	input [3:0] a, b;
	input cin;
	output [3:0] s;
	output cout;

	wire [3:0] s;
	wire cout;
	
	wire [3:0] p, g, c;

	PG_four pg(a, b, p, g);
	CLL cll(p, g, cin, c);
	XOR_Adder ad(a, b, c[2:0], cin, s);

	assign cout = c[3];

endmodule

9주차/tb_CLA.v
`timescale 1ns/10ps

module tb_CLA_four;
	reg [3:0] a, b;
	reg cin;
	wire [3:0] s;
	wire cout;

	CLA_four tb(a, b, cin, s, cout);

	initial
		begin
			$dumpfile("test_CLA_out.vcd");
			$dumpvars(-1, tb);
			$monitor("%b", s);
		end

	initial
		begin
			cin = 0;
			a = 4'b0000;	b = 4'b0000;	#10;
			a = 4'b0110;	b = 4'b0010;	#10;
			a = 4'b1100;	b = 4'b0010;	#10;
			a = 4'b0011;	b = 4'b1001;	#10;
			a = 4'b0110;	b = 4'b1111;	#10;
			a = 4'b0011;	b = 4'b1011;	#10;
			a = 4'b1001;	b = 4'b1100;	#10;
			cin = 1;
			a = 4'b0000;	b = 4'b0000;	#10;
			a = 4'b0110;	b = 4'b0010;	#10;
			a = 4'b1100;	b = 4'b0010;	#10;
			a = 4'b0011;	b = 4'b1001;	#10;
			a = 4'b0110;	b = 4'b1111;	#10;
			a = 4'b0011;	b = 4'b1011;	#10;
			a = 4'b1001;	b = 4'b1100;	#10;
		end

endmodule

9주차/test_CLA_out.vcd
$date
	Sun Nov 01 00:05:36 2020
$end
$version
	Icarus Verilog
$end
$timescale
	10ps
$end
$scope module tb_CLA_four $end
$scope module tb $end
$var wire 4 ! a [3:0] $end
$var wire 4 " b [3:0] $end
$var wire 1 # cin $end
$var wire 4 $ s [3:0] $end
$var wire 4 % p [3:0] $end
$var wire 4 & g [3:0] $end
$var wire 1 ' cout $end
$var wire 4 ( c [3:0] $end
$scope module ad $end
$var wire 4 ) a [3:0] $end
$var wire 4 * b [3:0] $end
$var wire 3 + c [2:0] $end
$var wire 1 # cin $end
$var wire 4 , s [3:0] $end
$upscope $end
$scope module cll $end
$var wire 1 # cin $end
$var wire 4 - p [3:0] $end
$var wire 4 . g [3:0] $end
$var reg 4 / cout [3:0] $end
$upscope $end
$scope module pg $end
$var wire 4 0 a [3:0] $end
$var wire 4 1 b [3:0] $end
$var wire 4 2 p [3:0] $end
$var wire 4 3 g [3:0] $end
$scope module pg0 $end
$var wire 1 4 a $end
$var wire 1 5 b $end
$var wire 1 6 g $end
$var wire 1 7 p $end
$upscope $end
$scope module pg1 $end
$var wire 1 8 a $end
$var wire 1 9 b $end
$var wire 1 : g $end
$var wire 1 ; p $end
$upscope $end
$scope module pg2 $end
$var wire 1 < a $end
$var wire 1 = b $end
$var wire 1 > g $end
$var wire 1 ? p $end
$upscope $end
$scope module pg3 $end
$var wire 1 @ a $end
$var wire 1 A b $end
$var wire 1 B g $end
$var wire 1 C p $end
$upscope $end
$upscope $end
$upscope $end
$upscope $end
$enddefinitions $end
#0
$dumpvars
0C
0B
0A
0@
0?
0>
0=
0<
0;
0:
09
08
07
06
05
04
b0 3
b0 2
b0 1
b0 0
b0 /
b0 .
b0 -
b0 ,
b0 +
b0 *
b0 )
b0 (
0'
b0 &
b0 %
b0 $
0#
b0 "
b0 !
$end
#1000
b110 +
b1000 $
b1000 ,
b110 (
b110 /
b10 &
b10 .
b10 3
1:
b100 %
b100 -
b100 2
1?
19
18
1<
b10 "
b10 *
b10 1
b110 !
b110 )
b110 0
#2000
b0 +
b1110 $
b1110 ,
b0 (
b0 /
1;
b0 &
b0 .
b0 3
0:
b1110 %
b1110 -
b1110 2
1C
08
1@
b1100 !
b1100 )
b1100 0
#3000
b11 +
b1100 $
b1100 ,
b11 (
b11 /
b1 &
b1 .
b1 3
16
b1010 %
b1010 -
b1010 2
0?
15
09
1A
14
18
0<
0@
b1001 "
b1001 *
b1001 1
b11 !
b11 )
b11 0
#4000
1'
b110 +
b101 $
b101 ,
b1110 (
b1110 /
0;
1:
b1001 %
b1001 -
b1001 2
17
06
b110 &
b110 .
b110 3
1>
19
1=
04
1<
b1111 "
b1111 *
b1111 1
b110 !
b110 )
b110 0
#5000
0'
b11 +
b1110 $
b1110 ,
b11 (
b11 /
b1000 %
b1000 -
b1000 2
07
16
b11 &
b11 .
b11 3
0>
0=
14
0<
b1011 "
b1011 *
b1011 1
b11 !
b11 )
b11 0
#6000
1'
b0 +
b101 $
b101 ,
b1000 (
b1000 /
17
06
1?
0:
b101 %
b101 -
b101 2
0C
b1000 &
b1000 .
b1000 3
1B
05
09
1=
08
1@
b1100 "
b1100 *
b1100 1
b1001 !
b1001 )
b1001 0
#7000
0'
b0 (
b0 /
0?
b0 %
b0 -
b0 2
07
b0 &
b0 .
b0 3
0B
0=
0A
04
0@
b1 $
b1 ,
b0 "
b0 *
b0 1
b0 !
b0 )
b0 0
1#
#8000
b110 +
b1001 $
b1001 ,
b110 (
b110 /
b10 &
b10 .
b10 3
1:
b100 %
b100 -
b100 2
1?
19
18
1<
b10 "
b10 *
b10 1
b110 !
b110 )
b110 0
#9000
b0 +
b1111 $
b1111 ,
b0 (
b0 /
1;
b0 &
b0 .
b0 3
0:
b1110 %
b1110 -
b1110 2
1C
08
1@
b1100 !
b1100 )
b1100 0
#10000
b11 +
b1101 $
b1101 ,
b11 (
b11 /
b1 &
b1 .
b1 3
16
b1010 %
b1010 -
b1010 2
0?
15
09
1A
14
18
0<
0@
b1001 "
b1001 *
b1001 1
b11 !
b11 )
b11 0
#11000
1'
b111 +
b110 $
b110 ,
b1111 (
b1111 /
0;
1:
b1001 %
b1001 -
b1001 2
17
06
b110 &
b110 .
b110 3
1>
19
1=
04
1<
b1111 "
b1111 *
b1111 1
b110 !
b110 )
b110 0
#12000
0'
b11 +
b1111 $
b1111 ,
b11 (
b11 /
b1000 %
b1000 -
b1000 2
07
16
b11 &
b11 .
b11 3
0>
0=
14
0<
b1011 "
b1011 *
b1011 1
b11 !
b11 )
b11 0
#13000
1'
b1 +
b110 $
b110 ,
b1001 (
b1001 /
17
06
1?
0:
b101 %
b101 -
b101 2
0C
b1000 &
b1000 .
b1000 3
1B
05
09
1=
08
1@
b1100 "
b1100 *
b1100 1
b1001 !
b1001 )
b1001 0
