13주차/sram.v
module sram(clk, cs, we, rd, addr, wr_data, rd_data);
	input	clk, cs, we, rd;
	input	[ADDRESS_BITS-1:0] addr;
	input	[DATA_WIDTH-1:0] wr_data;
	output	[DATA_WIDTH-1:0] rd_data;

	parameter	ADDRESS_BITS = 5, DATA_WIDTH = 8, NUM_REG = 32;

	reg	[DATA_WIDTH-1:0] mem[NUM_REG-1:0];
	reg	[DATA_WIDTH-1:0] data;

	always @ (posedge clk)
		begin
			if (cs&we)
				mem[addr] = wr_data;
			else if (cs&(!rd))
				data = mem[addr];
			else
				data = data;
		end
	
	assign rd_data = data;
endmodule

13주차/tb_sram.v
`timescale 1ns/10ps

module tb_sram;
	reg	clk, cs, we, rd;
	reg [4:0] addr;
	reg [7:0] wr_data;
	wire [7:0] rd_data;

	parameter	ADDRESS_BITS = 5, DATA_WIDTH = 8, NUM_REG = 32, STEP = 20;

	integer i;

	sram #(.ADDRESS_BITS(ADDRESS_BITS), .NUM_REG(NUM_REG), .DATA_WIDTH(DATA_WIDTH)) tb(clk, cs, we, rd, addr, wr_data, rd_data);

	initial
		begin
			$dumpfile("test_sram_out.vcd");
			$dumpvars(-1, tb);
			$monitor("%b", rd_data);
		end

	always
		#(STEP/2) clk = ~clk;

	initial
		begin
			clk =0; cs = 0; we = 0; rd = 1; #(STEP*2);
			
			cs = 1; we = 1; addr = 5'b00000; wr_data = 7'b0000000; #STEP;
			for (i = 0; i < 31; i = i+1)
				begin
					addr = addr+1;
					wr_data = wr_data+3;
					#STEP;
				end
			cs = 0; #(STEP*2);

			cs = 1; we = 0; rd = 0; #STEP;
			for(i = 0; i < 31; i = i+1)
				begin
					addr = addr - 1;
					#STEP;
				end
			$finish;
		end
endmodule

13주차/test_sram_out.vcd
$date
	Sun Nov 29 09:55:56 2020
$end
$version
	Icarus Verilog
$end
$timescale
	10ps
$end
$scope module tb_sram $end
$scope module tb $end
$var wire 5 ! addr [4:0] $end
$var wire 1 " clk $end
$var wire 1 # cs $end
$var wire 1 $ rd $end
$var wire 8 % rd_data [7:0] $end
$var wire 1 & we $end
$var wire 8 ' wr_data [7:0] $end
$var reg 8 ( data [7:0] $end
$upscope $end
$upscope $end
$enddefinitions $end
#0
$dumpvars
bx (
bx '
0&
bx %
1$
0#
0"
bx !
$end
#1000
1"
#2000
0"
#3000
1"
#4000
0"
b0 '
b0 !
1&
1#
#5000
1"
#6000
0"
b11 '
b1 !
#7000
1"
#8000
0"
b110 '
b10 !
#9000
1"
#10000
0"
b1001 '
b11 !
#11000
1"
#12000
0"
b1100 '
b100 !
#13000
1"
#14000
0"
b1111 '
b101 !
#15000
1"
#16000
0"
b10010 '
b110 !
#17000
1"
#18000
0"
b10101 '
b111 !
#19000
1"
#20000
0"
b11000 '
b1000 !
#21000
1"
#22000
0"
b11011 '
b1001 !
#23000
1"
#24000
0"
b11110 '
b1010 !
#25000
1"
#26000
0"
b100001 '
b1011 !
#27000
1"
#28000
0"
b100100 '
b1100 !
#29000
1"
#30000
0"
b100111 '
b1101 !
#31000
1"
#32000
0"
b101010 '
b1110 !
#33000
1"
#34000
0"
b101101 '
b1111 !
#35000
1"
#36000
0"
b110000 '
b10000 !
#37000
1"
#38000
0"
b110011 '
b10001 !
#39000
1"
#40000
0"
b110110 '
b10010 !
#41000
1"
#42000
0"
b111001 '
b10011 !
#43000
1"
#44000
0"
b111100 '
b10100 !
#45000
1"
#46000
0"
b111111 '
b10101 !
#47000
1"
#48000
0"
b1000010 '
b10110 !
#49000
1"
#50000
0"
b1000101 '
b10111 !
#51000
1"
#52000
0"
b1001000 '
b11000 !
#53000
1"
#54000
0"
b1001011 '
b11001 !
#55000
1"
#56000
0"
b1001110 '
b11010 !
#57000
1"
#58000
0"
b1010001 '
b11011 !
#59000
1"
#60000
0"
b1010100 '
b11100 !
#61000
1"
#62000
0"
b1010111 '
b11101 !
#63000
1"
#64000
0"
b1011010 '
b11110 !
#65000
1"
#66000
0"
b1011101 '
b11111 !
#67000
1"
#68000
0"
0#
#69000
1"
#70000
0"
#71000
1"
#72000
0"
0$
0&
1#
#73000
b1011101 %
b1011101 (
1"
#74000
0"
b11110 !
#75000
b1011010 %
b1011010 (
1"
#76000
0"
b11101 !
#77000
b1010111 %
b1010111 (
1"
#78000
0"
b11100 !
#79000
b1010100 %
b1010100 (
1"
#80000
0"
b11011 !
#81000
b1010001 %
b1010001 (
1"
#82000
0"
b11010 !
#83000
b1001110 %
b1001110 (
1"
#84000
0"
b11001 !
#85000
b1001011 %
b1001011 (
1"
#86000
0"
b11000 !
#87000
b1001000 %
b1001000 (
1"
#88000
0"
b10111 !
#89000
b1000101 %
b1000101 (
1"
#90000
0"
b10110 !
#91000
b1000010 %
b1000010 (
1"
#92000
0"
b10101 !
#93000
b111111 %
b111111 (
1"
#94000
0"
b10100 !
#95000
b111100 %
b111100 (
1"
#96000
0"
b10011 !
#97000
b111001 %
b111001 (
1"
#98000
0"
b10010 !
#99000
b110110 %
b110110 (
1"
#100000
0"
b10001 !
#101000
b110011 %
b110011 (
1"
#102000
0"
b10000 !
#103000
b110000 %
b110000 (
1"
#104000
0"
b1111 !
#105000
b101101 %
b101101 (
1"
#106000
0"
b1110 !
#107000
b101010 %
b101010 (
1"
#108000
0"
b1101 !
#109000
b100111 %
b100111 (
1"
#110000
0"
b1100 !
#111000
b100100 %
b100100 (
1"
#112000
0"
b1011 !
#113000
b100001 %
b100001 (
1"
#114000
0"
b1010 !
#115000
b11110 %
b11110 (
1"
#116000
0"
b1001 !
#117000
b11011 %
b11011 (
1"
#118000
0"
b1000 !
#119000
b11000 %
b11000 (
1"
#120000
0"
b111 !
#121000
b10101 %
b10101 (
1"
#122000
0"
b110 !
#123000
b10010 %
b10010 (
1"
#124000
0"
b101 !
#125000
b1111 %
b1111 (
1"
#126000
0"
b100 !
#127000
b1100 %
b1100 (
1"
#128000
0"
b11 !
#129000
b1001 %
b1001 (
1"
#130000
0"
b10 !
#131000
b110 %
b110 (
1"
#132000
0"
b1 !
#133000
b11 %
b11 (
1"
#134000
0"
b0 !
#135000
b0 %
b0 (
1"
