13주차/SequenceDetector.v
module SequenceDetector(clk, reset, in, out);
	input	clk, reset, in;
	output	out;
	wire	out;
	reg [2:0]	state;
	parameter S0=0, S1=1, S2=2, S3=3, S4=4;

	always @ (posedge clk or negedge reset)
		if (~reset)
			state = S0;
		else
			case (state)
				S0 : 	if (in)	state = S1;
					else	state = S0;
				S1 : 	if (in)	state = S2;
					else	state = S0;
				S2: 	if (in)	state = S3;
					else	state = S0;
				S3 : 	if (in)	state = S4;
					else	state = S0;
				S4 : 	if (in)	state = S4;
					else	state = S0;
			endcase
	assign out = (state == S4);
endmodule

13주차/tb_SequenceDetector.v
`timescale 1ns/10ps

module tb_SequenceDetector;
	reg	clk, reset, in;
	wire	out;

	SequenceDetector tb(clk, reset, in, out);

	initial
		begin
			$dumpfile("test_SequenceDetector_out.vcd");
			$dumpvars(-1, tb);
			$monitor("%b", out);
		end

	initial
		clk = 0;
	
	always
		#50 clk = !clk;

	initial
		begin
			reset = 1; in = 1; #50;
			reset = 0; in = 0; #70;
			reset = 1; in = 0; #100;
			reset = 1; in = 1; #100;
			reset = 1; in = 1; #100;
			reset = 1; in = 1; #100;
			reset = 1; in = 1; #100;
			reset = 1; in = 1; #100;
			reset = 1; in = 0; #100;
			reset = 1; in = 0; #100;
			reset = 1; in = 1; #100;
			reset = 1; in = 1; #100;
			reset = 1; in = 1; #100;
			reset = 1; in = 1; #100;
			$finish;
		end
endmodule

13주차/test_SequenceDetector_out.vcd
$date
	Sun Nov 29 11:08:10 2020
$end
$version
	Icarus Verilog
$end
$timescale
	10ps
$end
$scope module tb_SequenceDetector $end
$scope module tb $end
$var wire 1 ! clk $end
$var wire 1 " in $end
$var wire 1 # reset $end
$var wire 1 $ out $end
$var reg 3 % state [2:0] $end
$upscope $end
$upscope $end
$enddefinitions $end
#0
$dumpvars
bx %
x$
1#
1"
0!
$end
#5000
0$
b0 %
0"
0#
1!
#10000
0!
#12000
1#
#15000
1!
#20000
0!
#22000
1"
#25000
b1 %
1!
#30000
0!
#35000
b10 %
1!
#40000
0!
#45000
b11 %
1!
#50000
0!
#55000
1$
b100 %
1!
#60000
0!
#65000
1!
#70000
0!
#72000
0"
#75000
0$
b0 %
1!
#80000
0!
#85000
1!
#90000
0!
#92000
1"
#95000
b1 %
1!
#100000
0!
#105000
b10 %
1!
#110000
0!
#115000
b11 %
1!
#120000
0!
#125000
1$
b100 %
1!
