2주차/Halfsubtracter.v
module Halfsubtracter(x, y, d, b);

	input	x, y;
	output	d, b;

	assign d = x^y;
	assign b = ~x&y;

endmodule

2주차/Fullsubtracter_stru.v
module Fullsubtracter_stru(x, y, bin, d, b);

	input	x, y, bin;
	output	d, b;

	wire d0, b0, b1;

	Halfsubtracter h0(x, y, d0, b0);
	Halfsubtracter h1(d0, bin, d, b1);

	assign	b = b0|b1;

endmodule

2주차/tb_Fullsubtracter_stru.v
`timescale 1ns/10ps

module tb_Fullsubtracter_stru;
	reg	x, y, bin;
	wire	d, b;
	
	Fullsubtracter_stru tb(x, y, bin, d, b);

	initial
	begin
		$dumpfile("test_Fullsubtracter_stru_out.vcd");
		$dumpvars(-1,tb);
		$monitor("%b", d);
		$monitor("%b", b);
	end

	initial
		begin
			x = 0; y = 0; bin = 0; #100;
			x = 0; y = 1; bin = 0; #100;
			x = 1; y = 0; bin = 0; #100;
			x = 1; y = 1; bin = 0; #100;
			x = 0; y = 0; bin = 1; #100;
			x = 0; y = 1; bin = 1; #100;
			x = 1; y = 0; bin = 1; #100;
			x = 1; y = 1; bin = 1; #100;
		end

endmodule

2주차/test_Fullsubtracter_stru_out.vcd
$date
	Fri Sep 11 22:05:07 2020
$end
$version
	Icarus Verilog
$end
$timescale
	10ps
$end
$scope module tb_Fullsubtracter_stru $end
$scope module tb $end
$var wire 1 ! b $end
$var wire 1 " bin $end
$var wire 1 # x $end
$var wire 1 $ y $end
$var wire 1 % d0 $end
$var wire 1 & d $end
$var wire 1 ' b1 $end
$var wire 1 ( b0 $end
$scope module h0 $end
$var wire 1 ( b $end
$var wire 1 % d $end
$var wire 1 # x $end
$var wire 1 $ y $end
$upscope $end
$scope module h1 $end
$var wire 1 ' b $end
$var wire 1 & d $end
$var wire 1 % x $end
$var wire 1 " y $end
$upscope $end
$upscope $end
$upscope $end
$enddefinitions $end
#0
$dumpvars
0(
0'
0&
0%
0$
0#
0"
0!
$end
#10000
1&
1!
1%
1(
1$
#20000
0!
0(
0$
1#
#30000
0&
0%
1$
#40000
1!
1&
1'
1"
0$
0#
#50000
0'
0&
1%
1(
1$
#60000
0!
0(
0$
1#
#70000
1!
1'
1&
0%
1$
